hammPy/__init__.py
hammPy/hammPy.py
hammPy/core/__init__.py
hammPy/core/data/__init__.py
hammPy/core/data/frame.py
hammPy/core/interactions/__init__.py
hammPy/core/interactions/dynamic.py
hammPy/core/interactions/static.py
hammPy/core/validation/__init__.py
hammPy/core/validation/validation.py
hammPy/image/__init__.py
hammPy/image/image.py
hammPy/llms/__init__.py
hammPy/llms/completions/__init__.py
hammPy/llms/completions/openai/__init__.py
hammPy/llms/completions/openai/query.py
hammPy/llms/lib/__init__.py
hammPy/llms/lib/models.py
hammPy/pydantic/__init__.py
hammPy/pydantic/models.py
hammPy-0.1.30.13.dist-info/METADATA
hammPy-0.1.30.13.dist-info/WHEEL
hammPy-0.1.30.13.dist-info/top_level.txt
hammPy-0.1.30.13.dist-info/RECORD
