Metadata-Version: 2.1
Name: hammPy
Version: 0.1.30.13
Summary: Hammad's Python Tools
Author: Hammad Saeed
Author-email: hammad@supportvectors.com
Classifier: Programming Language :: Python :: 3
Classifier: License :: OSI Approved :: MIT License
Classifier: Operating System :: OS Independent
Requires-Python: >=3.10
Requires-Dist: aiohttp ==3.9.3
Requires-Dist: aiosignal ==1.3.1
Requires-Dist: annotated-types ==0.6.0
Requires-Dist: anyio ==4.2.0
Requires-Dist: async-timeout ==4.0.3
Requires-Dist: attrs ==23.2.0
Requires-Dist: certifi ==2024.2.2
Requires-Dist: charset-normalizer ==3.3.2
Requires-Dist: click ==8.1.7
Requires-Dist: colorama ==0.4.6
Requires-Dist: distro ==1.9.0
Requires-Dist: docstring-parser ==0.15
Requires-Dist: exceptiongroup ==1.2.0
Requires-Dist: frozenlist ==1.4.1
Requires-Dist: h11 ==0.14.0
Requires-Dist: httpcore ==1.0.3
Requires-Dist: httpx ==0.26.0
Requires-Dist: idna ==3.6
Requires-Dist: instructor ==0.5.2
Requires-Dist: markdown-it-py ==3.0.0
Requires-Dist: mdurl ==0.1.2
Requires-Dist: multidict ==6.0.5
Requires-Dist: numpy ==1.26.4
Requires-Dist: openai ==1.12.0
Requires-Dist: pandas ==2.2.0
Requires-Dist: pillow ==10.2.0
Requires-Dist: prompt-toolkit ==3.0.43
Requires-Dist: pydantic ==2.6.1
Requires-Dist: pydantic-core ==2.16.2
Requires-Dist: Pygments ==2.17.2
Requires-Dist: python-dateutil ==2.8.2
Requires-Dist: pytz ==2024.1
Requires-Dist: requests ==2.31.0
Requires-Dist: rich ==13.7.0
Requires-Dist: six ==1.16.0
Requires-Dist: sniffio ==1.3.0
Requires-Dist: tenacity ==8.2.3
Requires-Dist: tqdm ==4.66.2
Requires-Dist: typer ==0.9.0
Requires-Dist: typing-extensions ==4.9.0
Requires-Dist: tzdata ==2024.1
Requires-Dist: urllib3 ==2.2.0
Requires-Dist: wcwidth ==0.2.13
Requires-Dist: yarl ==1.9.4
